{"points":[{"cost":83480,"time":0.572},{"cost":83471,"time":0.978},{"cost":83463,"time":2.929},{"cost":83457,"time":4.253},{"cost":83449,"time":4.519},{"cost":83439,"time":4.601},{"cost":83434,"time":4.745},{"cost":83433,"time":5.253},{"cost":83428,"time":5.516},{"cost":83425,"time":5.597},{"cost":83417,"time":5.678},{"cost":83405,"time":27.079},{"cost":83399,"time":27.169},{"cost":83394,"time":28.906},{"cost":83384,"time":29.147},{"cost":83383,"time":212.027},{"cost":83379,"time":213.613},{"cost":83371,"time":285.639},{"cost":83346,"time":286.928},{"cost":83343,"time":419.291},{"cost":83342,"time":465.346},{"cost":83339,"time":494.137}]}