[[{"idleness": 817, "deallocated": 2227, "standing": 297}, {"idleness": 875, "deallocated": 2173, "standing": 297}, {"idleness": 860, "deallocated": 2185, "standing": 297}, {"idleness": 860, "deallocated": 2185, "standing": 297}, {"idleness": 860, "deallocated": 2185, "standing": 297}, {"idleness": 860, "deallocated": 2185, "standing": 297}, {"idleness": 860, "deallocated": 2185, "standing": 297}, {"idleness": 860, "deallocated": 2185, "standing": 297}, {"idleness": 860, "deallocated": 2185, "standing": 297}, {"idleness": 860, "deallocated": 2185, "standing": 297}, {"idleness": 860, "deallocated": 2185, "standing": 297}, {"idleness": 860, "deallocated": 2185, "standing": 297}, {"idleness": 860, "deallocated": 2185, "standing": 297}, {"idleness": 860, "deallocated": 2185, "standing": 297}, {"idleness": 860, "deallocated": 2185, "standing": 297}, {"idleness": 860, "deallocated": 2185, "standing": 297}, {"idleness": 860, "deallocated": 2185, "standing": 297}, {"idleness": 827, "deallocated": 2202, "standing": 297}, {"idleness": 827, "deallocated": 2202, "standing": 297}, {"idleness": 827, "deallocated": 2202, "standing": 297}, {"idleness": 803, "deallocated": 2249, "standing": 297}, {"idleness": 803, "deallocated": 2249, "standing": 297}, {"idleness": 811, "deallocated": 2247, "standing": 297}, {"idleness": 811, "deallocated": 2247, "standing": 297}, {"idleness": 811, "deallocated": 2247, "standing": 297}, {"idleness": 811, "deallocated": 2247, "standing": 297}]]