[{"value": 9389, "time": 0}, {"value": 9381, "time": 0.424831}, {"value": 9351, "time": 0.519576}, {"value": 9348, "time": 0.773896}, {"value": 9337, "time": 0.892578}, {"value": 9299, "time": 1.174823}, {"value": 9284, "time": 2.92404}, {"value": 9270, "time": 2.926139}, {"value": 9259, "time": 6.625242}, {"value": 9248, "time": 7.623604}, {"value": 9226, "time": 7.710376}, {"value": 9212, "time": 7.81509}, {"value": 9206, "time": 12.436725}, {"value": 9197, "time": 16.231541}, {"value": 9193, "time": 17.438345}, {"value": 9192, "time": 18.232188}, {"value": 9178, "time": 19.657375}, {"value": 9174, "time": 19.764088}, {"value": 9149, "time": 19.860864}, {"value": 9148, "time": 22.159679}, {"value": 9139, "time": 22.740127}, {"value": 9138, "time": 24.699922}, {"value": 9131, "time": 24.805602}, {"value": 9127, "time": 24.905333}, {"value": 9104, "time": 25.877768}, {"value": 9101, "time": 29.24572}, {"value": 9097, "time": 29.324543}, {"value": 9094, "time": 29.40034}, {"value": 9076, "time": 32.286618}, {"value": 9073, "time": 36.603071}, {"value": 9067, "time": 36.68485}, {"value": 9059, "time": 37.232354}, {"value": 9050, "time": 38.752319}, {"value": 9038, "time": 42.685798}, {"value": 9026, "time": 42.787524}, {"value": 8996, "time": 42.870271}, {"value": 8990, "time": 42.969004}, {"value": 8978, "time": 49.426763}, {"value": 8952, "time": 54.361525}, {"value": 8948, "time": 59.485854}, {"value": 8944, "time": 59.621453}, {"value": 8928, "time": 59.718226}, {"value": 8918, "time": 59.986508}, {"value": 8906, "time": 65.669271}, {"value": 8896, "time": 68.178559}, {"value": 8895, "time": 68.287301}, {"value": 8888, "time": 69.716443}, {"value": 8870, "time": 70.625014}, {"value": 8846, "time": 71.87866}, {"value": 8842, "time": 73.69583}, {"value": 8830, "time": 73.772626}, {"value": 8817, "time": 74.83794}, {"value": 8811, "time": 78.361315}, {"value": 8808, "time": 83.622272}, {"value": 8803, "time": 83.719016}, {"value": 8794, "time": 84.55113}, {"value": 8763, "time": 84.130912}, {"value": 8757, "time": 88.209966}, {"value": 8751, "time": 89.328972}, {"value": 8740, "time": 92.853543}, {"value": 8729, "time": 94.377465}, {"value": 8717, "time": 96.669333}, {"value": 8706, "time": 99.69942}, {"value": 8702, "time": 99.145739}, {"value": 8683, "time": 100.826244}, {"value": 8669, "time": 100.910019}, {"value": 8640, "time": 107.744734}, {"value": 8639, "time": 108.673248}, {"value": 8635, "time": 117.480685}, {"value": 8629, "time": 118.388225}, {"value": 8616, "time": 120.958382}, {"value": 8602, "time": 123.512552}, {"value": 8595, "time": 124.668457}, {"value": 8586, "time": 125.444378}, {"value": 8573, "time": 125.521172}, {"value": 8562, "time": 127.361219}, {"value": 8534, "time": 128.14911}, {"value": 8533, "time": 128.81832}, {"value": 8528, "time": 133.60969}, {"value": 8526, "time": 133.658402}, {"value": 8489, "time": 136.353192}, {"value": 8485, "time": 141.6655}, {"value": 8473, "time": 141.146369}, {"value": 8415, "time": 141.23912}, {"value": 8411, "time": 148.328122}, {"value": 8408, "time": 152.434171}, {"value": 8405, "time": 156.225031}, {"value": 8393, "time": 156.323761}, {"value": 8391, "time": 164.442044}, {"value": 8387, "time": 164.559728}, {"value": 8357, "time": 164.659461}, {"value": 8354, "time": 175.297997}, {"value": 8336, "time": 175.381774}, {"value": 8335, "time": 177.405359}, {"value": 8304, "time": 178.840488}, {"value": 8302, "time": 182.720108}, {"value": 8292, "time": 182.822833}, {"value": 8281, "time": 183.591776}, {"value": 8274, "time": 185.370052}, {"value": 8252, "time": 185.448839}, {"value": 8244, "time": 199.52444}, {"value": 8243, "time": 199.635884}, {"value": 8223, "time": 207.251508}, {"value": 8218, "time": 207.355199}, {"value": 8168, "time": 207.43402}, {"value": 8156, "time": 220.114062}, {"value": 8155, "time": 220.682539}, {"value": 8153, "time": 223.914927}, {"value": 8108, "time": 223.991719}, {"value": 8079, "time": 233.380246}, {"value": 8069, "time": 239.486973}, {"value": 8029, "time": 240.250818}, {"value": 8029, "time": 900}]