[[{"idleness": 616, "deallocated": 1991, "standing": 301}, {"idleness": 616, "deallocated": 1991, "standing": 301}, {"idleness": 584, "deallocated": 2009, "standing": 301}, {"idleness": 636, "deallocated": 1955, "standing": 301}, {"idleness": 666, "deallocated": 1911, "standing": 301}, {"idleness": 666, "deallocated": 1911, "standing": 301}, {"idleness": 666, "deallocated": 1911, "standing": 301}, {"idleness": 666, "deallocated": 1911, "standing": 301}, {"idleness": 666, "deallocated": 1911, "standing": 301}, {"idleness": 686, "deallocated": 1895, "standing": 301}, {"idleness": 655, "deallocated": 1922, "standing": 301}, {"idleness": 708, "deallocated": 1888, "standing": 301}, {"idleness": 708, "deallocated": 1888, "standing": 301}, {"idleness": 708, "deallocated": 1888, "standing": 301}, {"idleness": 708, "deallocated": 1888, "standing": 301}, {"idleness": 708, "deallocated": 1888, "standing": 301}, {"idleness": 708, "deallocated": 1888, "standing": 301}, {"idleness": 708, "deallocated": 1888, "standing": 301}, {"idleness": 708, "deallocated": 1888, "standing": 301}, {"idleness": 708, "deallocated": 1888, "standing": 301}, {"idleness": 708, "deallocated": 1888, "standing": 301}, {"idleness": 708, "deallocated": 1888, "standing": 301}, {"idleness": 708, "deallocated": 1888, "standing": 301}, {"idleness": 708, "deallocated": 1888, "standing": 301}, {"idleness": 708, "deallocated": 1888, "standing": 301}, {"idleness": 708, "deallocated": 1888, "standing": 301}, {"idleness": 708, "deallocated": 1888, "standing": 301}, {"idleness": 708, "deallocated": 1888, "standing": 301}, {"idleness": 708, "deallocated": 1888, "standing": 301}, {"idleness": 708, "deallocated": 1888, "standing": 301}, {"idleness": 708, "deallocated": 1888, "standing": 301}, {"idleness": 708, "deallocated": 1888, "standing": 301}, {"idleness": 708, "deallocated": 1888, "standing": 301}, {"idleness": 708, "deallocated": 1888, "standing": 301}, {"idleness": 708, "deallocated": 1888, "standing": 301}, {"idleness": 708, "deallocated": 1888, "standing": 301}, {"idleness": 708, "deallocated": 1888, "standing": 301}, {"idleness": 708, "deallocated": 1888, "standing": 301}, {"idleness": 708, "deallocated": 1888, "standing": 301}, {"idleness": 708, "deallocated": 1888, "standing": 301}, {"idleness": 683, "deallocated": 1903, "standing": 301}, {"idleness": 683, "deallocated": 1903, "standing": 301}, {"idleness": 683, "deallocated": 1903, "standing": 301}, {"idleness": 683, "deallocated": 1903, "standing": 301}, {"idleness": 683, "deallocated": 1903, "standing": 301}, {"idleness": 683, "deallocated": 1903, "standing": 301}, {"idleness": 683, "deallocated": 1903, "standing": 301}, {"idleness": 683, "deallocated": 1903, "standing": 301}, {"idleness": 683, "deallocated": 1903, "standing": 301}, {"idleness": 683, "deallocated": 1903, "standing": 301}, {"idleness": 683, "deallocated": 1903, "standing": 301}, {"idleness": 683, "deallocated": 1903, "standing": 301}, {"idleness": 683, "deallocated": 1903, "standing": 301}, {"idleness": 683, "deallocated": 1903, "standing": 301}, {"idleness": 683, "deallocated": 1903, "standing": 301}, {"idleness": 683, "deallocated": 1903, "standing": 301}, {"idleness": 683, "deallocated": 1903, "standing": 301}, {"idleness": 683, "deallocated": 1903, "standing": 301}, {"idleness": 683, "deallocated": 1903, "standing": 301}, {"idleness": 683, "deallocated": 1903, "standing": 301}, {"idleness": 683, "deallocated": 1903, "standing": 301}, {"idleness": 683, "deallocated": 1903, "standing": 301}, {"idleness": 683, "deallocated": 1903, "standing": 301}, {"idleness": 683, "deallocated": 1903, "standing": 301}, {"idleness": 683, "deallocated": 1903, "standing": 301}, {"idleness": 683, "deallocated": 1903, "standing": 301}, {"idleness": 683, "deallocated": 1903, "standing": 301}, {"idleness": 683, "deallocated": 1903, "standing": 301}, {"idleness": 683, "deallocated": 1903, "standing": 301}, {"idleness": 683, "deallocated": 1903, "standing": 301}, {"idleness": 683, "deallocated": 1903, "standing": 301}, {"idleness": 683, "deallocated": 1903, "standing": 301}, {"idleness": 683, "deallocated": 1903, "standing": 301}, {"idleness": 683, "deallocated": 1903, "standing": 301}]]