[[{"idleness": 894, "deallocated": 2228, "standing": 432}, {"idleness": 796, "deallocated": 2261, "standing": 432}, {"idleness": 796, "deallocated": 2261, "standing": 432}, {"idleness": 828, "deallocated": 2243, "standing": 432}, {"idleness": 828, "deallocated": 2243, "standing": 432}, {"idleness": 828, "deallocated": 2243, "standing": 432}, {"idleness": 828, "deallocated": 2243, "standing": 432}, {"idleness": 828, "deallocated": 2243, "standing": 432}, {"idleness": 838, "deallocated": 2236, "standing": 432}, {"idleness": 838, "deallocated": 2236, "standing": 432}, {"idleness": 838, "deallocated": 2236, "standing": 432}, {"idleness": 838, "deallocated": 2236, "standing": 432}, {"idleness": 838, "deallocated": 2236, "standing": 432}, {"idleness": 838, "deallocated": 2236, "standing": 432}, {"idleness": 838, "deallocated": 2236, "standing": 432}, {"idleness": 838, "deallocated": 2236, "standing": 432}, {"idleness": 838, "deallocated": 2236, "standing": 432}, {"idleness": 838, "deallocated": 2236, "standing": 432}, {"idleness": 838, "deallocated": 2236, "standing": 432}, {"idleness": 821, "deallocated": 2254, "standing": 432}, {"idleness": 821, "deallocated": 2254, "standing": 432}, {"idleness": 821, "deallocated": 2254, "standing": 432}, {"idleness": 822, "deallocated": 2253, "standing": 432}, {"idleness": 822, "deallocated": 2253, "standing": 432}, {"idleness": 853, "deallocated": 2234, "standing": 432}, {"idleness": 853, "deallocated": 2234, "standing": 432}, {"idleness": 853, "deallocated": 2234, "standing": 432}, {"idleness": 853, "deallocated": 2234, "standing": 432}, {"idleness": 853, "deallocated": 2234, "standing": 432}, {"idleness": 853, "deallocated": 2234, "standing": 432}, {"idleness": 853, "deallocated": 2234, "standing": 432}, {"idleness": 853, "deallocated": 2234, "standing": 432}, {"idleness": 853, "deallocated": 2234, "standing": 432}, {"idleness": 853, "deallocated": 2234, "standing": 432}, {"idleness": 826, "deallocated": 2251, "standing": 432}]]