[[{"idleness": 1111, "deallocated": 3527, "standing": 0}, {"idleness": 1198, "deallocated": 3488, "standing": 0}, {"idleness": 1166, "deallocated": 3501, "standing": 0}, {"idleness": 1166, "deallocated": 3501, "standing": 0}, {"idleness": 1097, "deallocated": 3549, "standing": 0}, {"idleness": 1097, "deallocated": 3549, "standing": 0}, {"idleness": 1097, "deallocated": 3549, "standing": 0}, {"idleness": 1097, "deallocated": 3549, "standing": 0}, {"idleness": 1097, "deallocated": 3549, "standing": 0}, {"idleness": 1106, "deallocated": 3533, "standing": 0}, {"idleness": 1066, "deallocated": 3553, "standing": 0}, {"idleness": 1171, "deallocated": 3492, "standing": 0}, {"idleness": 1171, "deallocated": 3492, "standing": 0}, {"idleness": 1171, "deallocated": 3492, "standing": 0}, {"idleness": 1132, "deallocated": 3508, "standing": 0}, {"idleness": 1132, "deallocated": 3508, "standing": 0}, {"idleness": 1132, "deallocated": 3508, "standing": 0}, {"idleness": 1132, "deallocated": 3508, "standing": 0}, {"idleness": 1132, "deallocated": 3508, "standing": 0}, {"idleness": 1132, "deallocated": 3508, "standing": 0}]]